pygraphia/__init__.py
pygraphia/algorithms/__init__.py
pygraphia/algorithms/bfs.py
pygraphia/algorithms/dfs.py
pygraphia/algorithms/mst.py
pygraphia/core/Edge.py
pygraphia/core/Graph.py
pygraphia/core/Path.py
pygraphia/core/Vertex.py
pygraphia/core/Walk.py
pygraphia/core/__init__.py
pygraphia-2023.1006a0.dist-info/LICENSE
pygraphia-2023.1006a0.dist-info/METADATA
pygraphia-2023.1006a0.dist-info/WHEEL
pygraphia-2023.1006a0.dist-info/top_level.txt
pygraphia-2023.1006a0.dist-info/RECORD
