Metadata-Version: 2.1
Name: pygraphia
Version: 2023.1006a0
Summary: A minimalist graph library
Author-email: Aniruddha Mukherjee <aniruddha.mukherji@outlook.com>
License: GPLv3
Project-URL: Homepage, https://github.com/amkhrjee/pygraphia
Keywords: graph,graph-algorithms
Classifier: Development Status :: 2 - Pre-Alpha
Classifier: License :: OSI Approved :: GNU General Public License v3 (GPLv3)
Classifier: Programming Language :: Python :: 3
Classifier: Operating System :: OS Independent
Classifier: Topic :: Scientific/Engineering :: Mathematics
Requires-Python: >=3.10
License-File: LICENSE
Provides-Extra: dev
Requires-Dist: mypy ; extra == 'dev'
Requires-Dist: autopep8 ; extra == 'dev'
Requires-Dist: userpath ; extra == 'dev'
Requires-Dist: bumpver ; extra == 'dev'
